pyham40k/__init__.py
pyham40k/main.py
pyham40k/cli/__init__.py
pyham40k/cli/cli_controller.py
pyham40k/cli/constants.py
pyham40k/cli/model/__init__.py
pyham40k/cli/model/cli_choice.py
pyham40k/cli/model/cli_file_prompt.py
pyham40k/cli/model/cli_prompt.py
pyham40k/core/__init__.py
pyham40k/core/calculator/__init__.py
pyham40k/core/calculator/base_calculator_strategy.py
pyham40k/core/calculator/floor_calculator.py
pyham40k/core/calculator/real_calculator.py
pyham40k/core/model/__init__.py
pyham40k/core/model/format_exception.py
pyham40k/core/model/reroll.py
pyham40k/core/model/attacker/__init__.py
pyham40k/core/model/attacker/attacker.py
pyham40k/core/model/attacker/attacker_builder.py
pyham40k/core/model/attacker/attacker_state.py
pyham40k/core/model/attacker/constants.py
pyham40k/core/model/defender/__init__.py
pyham40k/core/model/defender/constants.py
pyham40k/core/model/defender/defender.py
pyham40k/core/model/defender/defender_builder.py
pyham40k/core/model/defender/defender_state.py
pyham40k/core/model/value/__init__.py
pyham40k/core/model/value/base_value.py
pyham40k/core/model/value/non_positive_value.py
pyham40k/core/model/value/not_assigned_value.py
pyham40k/core/model/value/positive_value.py
pyham40k/core/model/value/random_value.py
pyham40k/core/model/value/simple_value.py
pyham40k/core/model/value/value_flyweight.py
pyham40k/core/parser/__init__.py
pyham40k/core/parser/simple_parser.py
pyham40k/core/parser/simple_scanner.py
pyham40k-1.1.0.dist-info/licenses/LICENSE
pyham40k-1.1.0.dist-info/METADATA
pyham40k-1.1.0.dist-info/WHEEL
pyham40k-1.1.0.dist-info/entry_points.txt
pyham40k-1.1.0.dist-info/top_level.txt
pyham40k-1.1.0.dist-info/RECORD
