Metadata-Version: 2.4
Name: pyham40k
Version: 1.1.0
Summary: pyham40k (pyham) - to overanalyze your Warhammer 40k 10e gameplay
Author-email: Cat Gamer <catgamer702@gmail.com>
License: MIT
Requires-Python: >=3.12
License-File: LICENSE
Requires-Dist: markdown-it-py==4.0.0
Requires-Dist: mdurl==0.1.2
Requires-Dist: Pygments==2.19.2
Requires-Dist: rich==14.1.0
Dynamic: license-file
